cxppython/__init__.py
cxppython/main.py
cxppython/bittensor/__init__.py
cxppython/bittensor/synapse.py
cxppython/core/__init__.py
cxppython/core/config.py
cxppython/utils/__init__.py
cxppython/utils/easy_imports.py
cxppython/utils/btlogging/__init__.py
cxppython/utils/btlogging/console.py
cxppython/utils/btlogging/defines.py
cxppython/utils/btlogging/format.py
cxppython/utils/btlogging/helpers.py
cxppython/utils/btlogging/loggingmachine.py
cxppython/utils/cxplogging/__init__.py
cxppython/utils/cxplogging/console.py
cxppython/utils/cxplogging/defines.py
cxppython/utils/cxplogging/format.py
cxppython/utils/cxplogging/helpers.py
cxppython/utils/cxplogging/loggingmachine.py
cxppython/utils/cxplogging/logginsimple.py
cxppython/utils/database/__init__.py
cxppython/utils/database/mongo_singleton.py
cxppython/utils/database/mysql.py
cxppython/utils/database/mysql_singleton.py
cxppython/utils/database/redis.py
modules/__init__.py
modules/data_entity_module.py
modules/ht_metadata_module.py
cxppython-0.2.10.dist-info/LICENSE
cxppython-0.2.10.dist-info/METADATA
cxppython-0.2.10.dist-info/WHEEL
cxppython-0.2.10.dist-info/top_level.txt
cxppython-0.2.10.dist-info/RECORD
